Metadata-Version: 2.1
Name: pysnmplib
Version: 5.0.23
Summary: 
Home-page: https://github.com/pysnmp/pysnmp
License: BSD-2-Clause
Author: omrozowicz
Author-email: omrozowicz@splunk.com
Requires-Python: >=3.8,<4.0
Classifier: Development Status :: 5 - Production/Stable
Classifier: Environment :: Console
Classifier: Intended Audience :: Developers
Classifier: Intended Audience :: Information Technology
Classifier: Intended Audience :: System Administrators
Classifier: Intended Audience :: Telecommunications Industry
Classifier: License :: OSI Approved :: BSD License
Classifier: Natural Language :: English
Classifier: Operating System :: OS Independent
Classifier: Programming Language :: Python :: 3
Classifier: Programming Language :: Python :: 3.8
Classifier: Programming Language :: Python :: 3.9
Classifier: Programming Language :: Python :: 3.10
Classifier: Programming Language :: Python :: 3.11
Classifier: Topic :: Communications
Classifier: Topic :: Software Development :: Libraries :: Python Modules
Requires-Dist: pycryptodomex (>=3.11.0,<4.0.0)
Requires-Dist: pysnmp-pyasn1 (>=1.1.3,<2.0.0)
Requires-Dist: pysnmp-pysmi (>=1.0.4,<2.0.0)
Project-URL: Repository, https://github.com/pysnmp/pysnmp
